{
  "timestamp": 187,
  "video_source": "20240720_einsatz_1080p",
  "emergency_active": true,
  "scenario_type": "highway",
  "vehicles": [
    {
      "id": 9551,
      "type": "truck",
      "x_meters": 2.69,
      "y_meters": 7.09,
      "position_reliable": true,
      "speed_kmh": 0.0,
      "forward_speed_ms": 0.0,
      "lateral_speed_ms": 0.0,
      "acceleration": 0.0,
      "jerk": 0.0,
      "ttc_to_ego": null,
      "lane_id": 3,
      "lateral_offset": -1.06,
      "distance_to_ego": 7.58,
      "lanes_total": 3,
      "road_type": "highway",
      "lane_source": "config",
      "preceding_id": null,
      "following_id": null,
      "left_preceding_id": 8252,
      "left_following_id": null,
      "right_preceding_id": 9554,
      "right_following_id": null,
      "behaviour": "failed_to_yield",
      "bbox": [
        768,
        0,
        1135,
        614
      ]
    },
    {
      "id": 9554,
      "type": "car",
      "x_meters": 6.77,
      "y_meters": 9.7,
      "position_reliable": true,
      "speed_kmh": 0.0,
      "forward_speed_ms": 0.0,
      "lateral_speed_ms": 0.0,
      "acceleration": 0.0,
      "jerk": 0.0,
      "ttc_to_ego": null,
      "lane_id": 3,
      "lateral_offset": 3.02,
      "distance_to_ego": 11.83,
      "lanes_total": 3,
      "road_type": "highway",
      "lane_source": "config",
      "preceding_id": null,
      "following_id": null,
      "left_preceding_id": 8252,
      "left_following_id": 9551,
      "right_preceding_id": null,
      "right_following_id": null,
      "behaviour": "normal",
      "bbox": [
        1225,
        419,
        1265,
        565
      ]
    }
  ]
}