{
  "timestamp": 372,
  "video_source": "20240720_einsatz_1080p",
  "emergency_active": true,
  "scenario_type": "highway",
  "vehicles": [
    {
      "id": 2563,
      "type": "truck",
      "x_meters": 2.67,
      "y_meters": 12.84,
      "position_reliable": true,
      "speed_kmh": 2.27,
      "forward_speed_ms": -0.63,
      "lateral_speed_ms": -0.06,
      "acceleration": 0.31,
      "jerk": 0.123,
      "lane_id": 2,
      "lateral_offset": 1.38,
      "distance_to_ego": 13.11,
      "lanes_total": 3,
      "road_type": "highway",
      "lane_source": "config",
      "preceding_id": 2647,
      "following_id": 1967,
      "left_preceding_id": 2808,
      "left_following_id": 9440,
      "right_preceding_id": null,
      "right_following_id": null,
      "behaviour": "failed_to_yield",
      "bbox": [
        1052,
        236,
        1339,
        566
      ]
    },
    {
      "id": 2647,
      "type": "truck",
      "x_meters": 2.28,
      "y_meters": 30.2,
      "position_reliable": true,
      "speed_kmh": 28.04,
      "forward_speed_ms": -7.78,
      "lateral_speed_ms": -0.35,
      "acceleration": -1.44,
      "jerk": 5.93,
      "lane_id": 2,
      "lateral_offset": 0.19,
      "distance_to_ego": 30.29,
      "lanes_total": 3,
      "road_type": "highway",
      "lane_source": "config",
      "preceding_id": null,
      "following_id": 2563,
      "left_preceding_id": null,
      "left_following_id": 2808,
      "right_preceding_id": null,
      "right_following_id": null,
      "behaviour": "normal",
      "bbox": [
        926,
        308,
        1061,
        484
      ]
    },
    {
      "id": 1967,
      "type": "truck",
      "x_meters": 3.31,
      "y_meters": 7.27,
      "position_reliable": false,
      "speed_kmh": 1.01,
      "forward_speed_ms": -0.28,
      "lateral_speed_ms": 0.0,
      "acceleration": 0.18,
      "jerk": -0.05,
      "lane_id": 3,
      "lateral_offset": -0.29,
      "distance_to_ego": 7.99,
      "lanes_total": 3,
      "road_type": "highway",
      "lane_source": "config",
      "preceding_id": 2563,
      "following_id": null,
      "left_preceding_id": 9440,
      "left_following_id": null,
      "right_preceding_id": null,
      "right_following_id": null,
      "behaviour": "failed_to_yield",
      "bbox": [
        1182,
        2,
        1920,
        691
      ]
    },
    {
      "id": 2808,
      "type": "car",
      "x_meters": -2.14,
      "y_meters": 23.66,
      "position_reliable": true,
      "speed_kmh": 8.83,
      "forward_speed_ms": 2.44,
      "lateral_speed_ms": -0.25,
      "acceleration": 2.44,
      "jerk": 2.44,
      "lane_id": 2,
      "lateral_offset": -1.01,
      "distance_to_ego": 23.76,
      "lanes_total": 3,
      "road_type": "highway",
      "lane_source": "config",
      "preceding_id": null,
      "following_id": 9440,
      "left_preceding_id": null,
      "left_following_id": null,
      "right_preceding_id": 2647,
      "right_following_id": 2563,
      "behaviour": "normal",
      "bbox": [
        746,
        417,
        830,
        492
      ]
    },
    {
      "id": 9440,
      "type": "car",
      "x_meters": -2.23,
      "y_meters": 11.96,
      "position_reliable": true,
      "speed_kmh": 0.0,
      "forward_speed_ms": 0.0,
      "lateral_speed_ms": 0.0,
      "acceleration": 0.0,
      "jerk": 0.0,
      "lane_id": 2,
      "lateral_offset": -1.85,
      "distance_to_ego": 12.17,
      "lanes_total": 3,
      "road_type": "highway",
      "lane_source": "config",
      "preceding_id": 2808,
      "following_id": null,
      "left_preceding_id": null,
      "left_following_id": null,
      "right_preceding_id": 2563,
      "right_following_id": 1967,
      "behaviour": "normal",
      "bbox": [
        534,
        409,
        755,
        583
      ]
    }
  ]
}