{
  "timestamp": 386,
  "video_source": "20240720_einsatz_1080p",
  "emergency_active": true,
  "scenario_type": "highway",
  "vehicles": [
    {
      "id": 9902,
      "type": "truck",
      "x_meters": 2.03,
      "y_meters": 4.08,
      "position_reliable": false,
      "speed_kmh": 1.69,
      "forward_speed_ms": -0.46,
      "lateral_speed_ms": -0.1,
      "acceleration": 2.07,
      "jerk": 0.09,
      "ttc_to_ego": 8.87,
      "lane_id": 3,
      "lateral_offset": -1.72,
      "distance_to_ego": 4.56,
      "lanes_total": 3,
      "road_type": "highway",
      "lane_source": "config",
      "preceding_id": null,
      "following_id": null,
      "left_preceding_id": null,
      "left_following_id": null,
      "right_preceding_id": null,
      "right_following_id": null,
      "behaviour": "failed_to_yield",
      "bbox": [
        792,
        0,
        1278,
        713
      ]
    }
  ]
}