{
  "timestamp": 432,
  "video_source": "20240720_einsatz_1080p",
  "emergency_active": true,
  "scenario_type": "highway",
  "vehicles": [
    {
      "id": 16692,
      "type": "truck",
      "x_meters": -1.38,
      "y_meters": 5.57,
      "position_reliable": true,
      "speed_kmh": 2.81,
      "forward_speed_ms": 0.67,
      "lateral_speed_ms": 0.4,
      "acceleration": 0.37,
      "jerk": 0.11,
      "ttc_to_ego": null,
      "lane_id": 2,
      "lateral_offset": -1.38,
      "distance_to_ego": 5.74,
      "lanes_total": 3,
      "road_type": "highway",
      "lane_source": "config",
      "preceding_id": null,
      "following_id": null,
      "left_preceding_id": null,
      "left_following_id": null,
      "right_preceding_id": null,
      "right_following_id": 17310,
      "behaviour": "failed_to_yield",
      "bbox": [
        147,
        1,
        528,
        669
      ]
    },
    {
      "id": 17310,
      "type": "truck",
      "x_meters": 1.62,
      "y_meters": 4.95,
      "position_reliable": true,
      "speed_kmh": 1.15,
      "forward_speed_ms": -0.22,
      "lateral_speed_ms": 0.23,
      "acceleration": -0.13,
      "jerk": -0.02,
      "ttc_to_ego": 22.5,
      "lane_id": 2,
      "lateral_offset": 1.62,
      "distance_to_ego": 5.21,
      "lanes_total": 3,
      "road_type": "highway",
      "lane_source": "config",
      "preceding_id": null,
      "following_id": null,
      "left_preceding_id": 16692,
      "left_following_id": null,
      "right_preceding_id": null,
      "right_following_id": null,
      "behaviour": "failed_to_yield",
      "bbox": [
        646,
        1,
        1161,
        696
      ]
    }
  ]
}