{
  "timestamp": 518,
  "video_source": "20240720_einsatz_1080p",
  "emergency_active": true,
  "scenario_type": "highway",
  "vehicles": [
    {
      "id": 3467,
      "type": "truck",
      "x_meters": -3.28,
      "y_meters": 10.1,
      "position_reliable": true,
      "speed_kmh": 0.95,
      "forward_speed_ms": -0.26,
      "lateral_speed_ms": 0.04,
      "acceleration": 0.05,
      "jerk": 0.16,
      "lane_id": 1,
      "lateral_offset": 0.76,
      "distance_to_ego": 10.62,
      "lanes_total": 3,
      "road_type": "highway",
      "lane_source": "config",
      "preceding_id": 3497,
      "following_id": null,
      "left_preceding_id": null,
      "left_following_id": null,
      "right_preceding_id": 3401,
      "right_following_id": null,
      "behaviour": "failed_to_yield",
      "bbox": [
        131,
        0,
        769,
        627
      ]
    },
    {
      "id": 3401,
      "type": "truck",
      "x_meters": 1.45,
      "y_meters": 10.4,
      "position_reliable": true,
      "speed_kmh": 1.23,
      "forward_speed_ms": -0.34,
      "lateral_speed_ms": 0.02,
      "acceleration": 0.01,
      "jerk": 0.05,
      "lane_id": 2,
      "lateral_offset": 0.81,
      "distance_to_ego": 10.5,
      "lanes_total": 3,
      "road_type": "highway",
      "lane_source": "config",
      "preceding_id": null,
      "following_id": null,
      "left_preceding_id": 3497,
      "left_following_id": 3467,
      "right_preceding_id": 2647,
      "right_following_id": null,
      "behaviour": "failed_to_yield",
      "bbox": [
        845,
        12,
        1353,
        611
      ]
    },
    {
      "id": 2647,
      "type": "truck",
      "x_meters": 7.11,
      "y_meters": 14.1,
      "position_reliable": true,
      "speed_kmh": 1.93,
      "forward_speed_ms": -0.53,
      "lateral_speed_ms": -0.08,
      "acceleration": 0.16,
      "jerk": 0.24,
      "lane_id": 3,
      "lateral_offset": 0.04,
      "distance_to_ego": 15.79,
      "lanes_total": 3,
      "road_type": "highway",
      "lane_source": "config",
      "preceding_id": null,
      "following_id": null,
      "left_preceding_id": 3497,
      "left_following_id": 3401,
      "right_preceding_id": null,
      "right_following_id": null,
      "behaviour": "failed_to_yield",
      "bbox": [
        1298,
        0,
        1916,
        559
      ]
    },
    {
      "id": 3480,
      "type": "car",
      "x_meters": -3.98,
      "y_meters": 42.98,
      "position_reliable": true,
      "speed_kmh": 2.02,
      "forward_speed_ms": 0.56,
      "lateral_speed_ms": 0.0,
      "acceleration": 0.95,
      "jerk": -0.05,
      "lane_id": 2,
      "lateral_offset": -1.09,
      "distance_to_ego": 43.16,
      "lanes_total": 3,
      "road_type": "highway",
      "lane_source": "config",
      "preceding_id": null,
      "following_id": 3497,
      "left_preceding_id": null,
      "left_following_id": null,
      "right_preceding_id": null,
      "right_following_id": 2647,
      "behaviour": "normal",
      "bbox": [
        755,
        425,
        794,
        467
      ]
    },
    {
      "id": 3497,
      "type": "car",
      "x_meters": -3.86,
      "y_meters": 34.88,
      "position_reliable": true,
      "speed_kmh": 1.65,
      "forward_speed_ms": -0.45,
      "lateral_speed_ms": 0.09,
      "acceleration": 0.11,
      "jerk": 0.67,
      "lane_id": 2,
      "lateral_offset": -1.23,
      "distance_to_ego": 35.09,
      "lanes_total": 3,
      "road_type": "highway",
      "lane_source": "config",
      "preceding_id": 3480,
      "following_id": 3467,
      "left_preceding_id": null,
      "left_following_id": null,
      "right_preceding_id": null,
      "right_following_id": 2647,
      "behaviour": "normal",
      "bbox": [
        737,
        414,
        763,
        477
      ]
    }
  ]
}