{
  "timestamp": 595,
  "video_source": "20240720_einsatz_1080p",
  "emergency_active": true,
  "scenario_type": "highway",
  "vehicles": [
    {
      "id": 3988,
      "type": "car",
      "x_meters": -3.85,
      "y_meters": 8.21,
      "position_reliable": true,
      "speed_kmh": 0.0,
      "forward_speed_ms": 0.0,
      "lateral_speed_ms": 0.0,
      "acceleration": 0.0,
      "jerk": 0.0,
      "lane_id": 1,
      "lateral_offset": -0.39,
      "distance_to_ego": 9.07,
      "lanes_total": 3,
      "road_type": "highway",
      "lane_source": "config",
      "preceding_id": 3941,
      "following_id": null,
      "left_preceding_id": null,
      "left_following_id": null,
      "right_preceding_id": 3827,
      "right_following_id": null,
      "behaviour": "normal",
      "bbox": [
        102,
        278,
        405,
        657
      ]
    },
    {
      "id": 3941,
      "type": "car",
      "x_meters": -2.59,
      "y_meters": 30.33,
      "position_reliable": true,
      "speed_kmh": 2.32,
      "forward_speed_ms": -0.34,
      "lateral_speed_ms": 0.55,
      "acceleration": -0.031,
      "jerk": -0.003,
      "lane_id": 2,
      "lateral_offset": -1.03,
      "distance_to_ego": 30.44,
      "lanes_total": 3,
      "road_type": "highway",
      "lane_source": "config",
      "preceding_id": null,
      "following_id": 3988,
      "left_preceding_id": null,
      "left_following_id": null,
      "right_preceding_id": null,
      "right_following_id": 3827,
      "behaviour": "yielded",
      "bbox": [
        741,
        431,
        828,
        485
      ]
    },
    {
      "id": 3827,
      "type": "truck",
      "x_meters": 2.93,
      "y_meters": 8.23,
      "position_reliable": true,
      "speed_kmh": 1.76,
      "forward_speed_ms": -0.49,
      "lateral_speed_ms": 0.01,
      "acceleration": -0.62,
      "jerk": -0.21,
      "lane_id": 3,
      "lateral_offset": -0.91,
      "distance_to_ego": 8.74,
      "lanes_total": 3,
      "road_type": "highway",
      "lane_source": "config",
      "preceding_id": null,
      "following_id": null,
      "left_preceding_id": 3941,
      "left_following_id": 3988,
      "right_preceding_id": null,
      "right_following_id": null,
      "behaviour": "failed_to_yield",
      "bbox": [
        1063,
        13,
        1827,
        680
      ]
    }
  ]
}