{
  "timestamp": 636,
  "video_source": "20240720_einsatz_1080p",
  "emergency_active": true,
  "scenario_type": "highway",
  "vehicles": [
    {
      "id": 22919,
      "type": "truck",
      "x_meters": 1.99,
      "y_meters": 6.83,
      "position_reliable": true,
      "speed_kmh": 21.17,
      "forward_speed_ms": -5.86,
      "lateral_speed_ms": 0.5,
      "acceleration": 0.21,
      "jerk": 6.28,
      "ttc_to_ego": 1.17,
      "lane_id": 3,
      "lateral_offset": -1.76,
      "distance_to_ego": 7.11,
      "lanes_total": 3,
      "road_type": "highway",
      "lane_source": "config",
      "preceding_id": null,
      "following_id": null,
      "left_preceding_id": null,
      "left_following_id": null,
      "right_preceding_id": null,
      "right_following_id": null,
      "behaviour": "failed_to_yield",
      "bbox": [
        664,
        0,
        1270,
        684
      ]
    }
  ]
}