{
  "timestamp": 672,
  "video_source": "20240720_einsatz_1080p",
  "emergency_active": true,
  "scenario_type": "highway",
  "vehicles": [
    {
      "id": 4156,
      "type": "truck",
      "x_meters": 3.22,
      "y_meters": 7.46,
      "position_reliable": true,
      "speed_kmh": 1.03,
      "forward_speed_ms": 0.25,
      "lateral_speed_ms": 0.14,
      "acceleration": 0.13,
      "jerk": 0.03,
      "lane_id": 3,
      "lateral_offset": -0.54,
      "distance_to_ego": 8.13,
      "lanes_total": 3,
      "road_type": "highway",
      "lane_source": "config",
      "preceding_id": null,
      "following_id": null,
      "left_preceding_id": 9641,
      "left_following_id": null,
      "right_preceding_id": null,
      "right_following_id": null,
      "behaviour": "yielded",
      "bbox": [
        1107,
        1,
        1907,
        692
      ]
    },
    {
      "id": 9640,
      "type": "car",
      "x_meters": -8.62,
      "y_meters": 43.2,
      "position_reliable": false,
      "speed_kmh": 0.0,
      "forward_speed_ms": 0.0,
      "lateral_speed_ms": 0.0,
      "acceleration": 0.0,
      "jerk": 0.0,
      "lane_id": 1,
      "lateral_offset": 0.94,
      "distance_to_ego": 44.05,
      "lanes_total": 3,
      "road_type": "highway",
      "lane_source": "config",
      "preceding_id": null,
      "following_id": 9641,
      "left_preceding_id": null,
      "left_following_id": null,
      "right_preceding_id": null,
      "right_following_id": 4156,
      "behaviour": "normal",
      "bbox": [
        425,
        412,
        535,
        466
      ]
    },
    {
      "id": 9641,
      "type": "car",
      "x_meters": -8.62,
      "y_meters": 34.07,
      "position_reliable": false,
      "speed_kmh": 0.0,
      "forward_speed_ms": 0.0,
      "lateral_speed_ms": 0.0,
      "acceleration": 0.0,
      "jerk": 0.0,
      "lane_id": 1,
      "lateral_offset": -1.62,
      "distance_to_ego": 35.14,
      "lanes_total": 3,
      "road_type": "highway",
      "lane_source": "config",
      "preceding_id": 9640,
      "following_id": null,
      "left_preceding_id": null,
      "left_following_id": null,
      "right_preceding_id": null,
      "right_following_id": 4156,
      "behaviour": "normal",
      "bbox": [
        1,
        400,
        87,
        478
      ]
    }
  ]
}