{
  "timestamp": 705,
  "video_source": "20240720_einsatz_1080p",
  "emergency_active": true,
  "scenario_type": "highway",
  "vehicles": [
    {
      "id": 25566,
      "type": "car",
      "x_meters": -1.38,
      "y_meters": 13.18,
      "position_reliable": true,
      "speed_kmh": 0.0,
      "forward_speed_ms": 0.0,
      "lateral_speed_ms": 0.0,
      "acceleration": 0.0,
      "jerk": 0.0,
      "ttc_to_ego": null,
      "lane_id": 2,
      "lateral_offset": -1.38,
      "distance_to_ego": 13.25,
      "lanes_total": 3,
      "road_type": "highway",
      "lane_source": "config",
      "preceding_id": null,
      "following_id": 25501,
      "left_preceding_id": null,
      "left_following_id": null,
      "right_preceding_id": null,
      "right_following_id": null,
      "behaviour": "normal",
      "bbox": [
        470,
        429,
        541,
        530
      ]
    },
    {
      "id": 25501,
      "type": "car",
      "x_meters": -1.52,
      "y_meters": 6.48,
      "position_reliable": true,
      "speed_kmh": 12.85,
      "forward_speed_ms": -3.57,
      "lateral_speed_ms": -0.02,
      "acceleration": 0.02,
      "jerk": 3.61,
      "ttc_to_ego": 1.82,
      "lane_id": 2,
      "lateral_offset": -1.52,
      "distance_to_ego": 6.66,
      "lanes_total": 3,
      "road_type": "highway",
      "lane_source": "config",
      "preceding_id": 25566,
      "following_id": null,
      "left_preceding_id": null,
      "left_following_id": null,
      "right_preceding_id": null,
      "right_following_id": null,
      "behaviour": "failed_to_yield",
      "bbox": [
        291,
        415,
        493,
        642
      ]
    }
  ]
}