{
  "timestamp": 703,
  "video_source": "20240720_einsatz_1080p",
  "emergency_active": true,
  "scenario_type": "highway",
  "vehicles": [
    {
      "id": 25501,
      "type": "car",
      "x_meters": -1.53,
      "y_meters": 13.64,
      "position_reliable": true,
      "speed_kmh": 0.0,
      "forward_speed_ms": 0.0,
      "lateral_speed_ms": 0.0,
      "acceleration": 0.0,
      "jerk": 0.0,
      "ttc_to_ego": null,
      "lane_id": 2,
      "lateral_offset": -1.53,
      "distance_to_ego": 13.73,
      "lanes_total": 3,
      "road_type": "highway",
      "lane_source": "config",
      "preceding_id": null,
      "following_id": 25459,
      "left_preceding_id": null,
      "left_following_id": null,
      "right_preceding_id": null,
      "right_following_id": 10454,
      "behaviour": "normal",
      "bbox": [
        464,
        431,
        534,
        526
      ]
    },
    {
      "id": 25459,
      "type": "car",
      "x_meters": -1.56,
      "y_meters": 6.97,
      "position_reliable": true,
      "speed_kmh": 13.79,
      "forward_speed_ms": -3.83,
      "lateral_speed_ms": -0.02,
      "acceleration": -3.83,
      "jerk": -3.83,
      "ttc_to_ego": 1.82,
      "lane_id": 2,
      "lateral_offset": -1.56,
      "distance_to_ego": 7.14,
      "lanes_total": 3,
      "road_type": "highway",
      "lane_source": "config",
      "preceding_id": 25501,
      "following_id": null,
      "left_preceding_id": null,
      "left_following_id": null,
      "right_preceding_id": null,
      "right_following_id": 10454,
      "behaviour": "braked_abruptly",
      "bbox": [
        303,
        422,
        497,
        621
      ]
    },
    {
      "id": 10454,
      "type": "truck",
      "x_meters": 2.11,
      "y_meters": 4.58,
      "position_reliable": true,
      "speed_kmh": 0.0,
      "forward_speed_ms": 0.0,
      "lateral_speed_ms": 0.0,
      "acceleration": 0.0,
      "jerk": 0.0,
      "ttc_to_ego": null,
      "lane_id": 3,
      "lateral_offset": -1.64,
      "distance_to_ego": 5.04,
      "lanes_total": 3,
      "road_type": "highway",
      "lane_source": "config",
      "preceding_id": null,
      "following_id": null,
      "left_preceding_id": 25459,
      "left_following_id": null,
      "right_preceding_id": null,
      "right_following_id": null,
      "behaviour": "normal",
      "bbox": [
        774,
        2,
        1277,
        717
      ]
    }
  ]
}