{
  "timestamp": 54,
  "video_source": "20240720_\ud83d\udea8\ud83d\ude91Einsatzfahrt durch ",
  "emergency_active": true,
  "scenario_type": "highway",
  "vehicles": [
    {
      "id": 14,
      "type": "truck",
      "x_meters": 2.55,
      "y_meters": 6.7,
      "speed_kmh": 0.91,
      "acceleration": -1.51,
      "jerk": -0.8,
      "heading_angle": 0.0,
      "lane_id": 3,
      "lateral_offset": -0.32,
      "distance_to_ego": 9.89,
      "is_emergency": false,
      "behaviour": "failed_to_yield",
      "bbox": [
        391,
        0,
        640,
        224
      ]
    },
    {
      "id": 147,
      "type": "car",
      "x_meters": -1.8,
      "y_meters": 15.58,
      "speed_kmh": 0.58,
      "acceleration": 0.13,
      "jerk": -0.32,
      "heading_angle": 0.0,
      "lane_id": 2,
      "lateral_offset": -1.04,
      "distance_to_ego": 8.66,
      "is_emergency": false,
      "behaviour": "failed_to_yield",
      "bbox": [
        245,
        139,
        277,
        163
      ]
    },
    {
      "id": 83,
      "type": "truck",
      "x_meters": 1.27,
      "y_meters": 13.78,
      "speed_kmh": 0.88,
      "acceleration": 0.65,
      "jerk": 1.32,
      "heading_angle": 0.0,
      "lane_id": 2,
      "lateral_offset": 0.83,
      "distance_to_ego": 9.18,
      "is_emergency": false,
      "behaviour": "failed_to_yield",
      "bbox": [
        317,
        71,
        417,
        169
      ]
    }
  ]
}