{
  "timestamp": 105,
  "video_source": "20240720_\ud83d\udea8\ud83d\ude91Einsatzfahrt durch ",
  "emergency_active": true,
  "emergency_triggered_by": [
    "siren"
  ],
  "scenario_type": "highway",
  "vehicles": [
    {
      "id": 264,
      "type": "car",
      "x_meters": 0.21,
      "y_meters": 0.88,
      "speed_kmh": 0.1599999964237213,
      "acceleration": 0.014000000432133675,
      "jerk": 0.03099999949336052,
      "heading_angle": 0.0,
      "lane_id": 3,
      "lateral_offset": -1.59,
      "distance_to_ego": 0.9,
      "behaviour": "failed_to_yield",
      "bbox": [
        371,
        117,
        516,
        208
      ]
    },
    {
      "id": 198,
      "type": "car",
      "x_meters": -0.04,
      "y_meters": 0.37,
      "speed_kmh": 0.009999999776482582,
      "acceleration": 0.0,
      "jerk": -0.003000000026077032,
      "heading_angle": 0.0,
      "lane_id": 2,
      "lateral_offset": -1.0,
      "distance_to_ego": 0.37,
      "behaviour": "failed_to_yield",
      "bbox": [
        246,
        134,
        281,
        164
      ]
    },
    {
      "id": 191,
      "type": "car",
      "x_meters": -0.1,
      "y_meters": 0.58,
      "speed_kmh": 0.009999999776482582,
      "acceleration": 0.0,
      "jerk": 0.003000000026077032,
      "heading_angle": 0.0,
      "lane_id": 2,
      "lateral_offset": -1.6,
      "distance_to_ego": 0.59,
      "behaviour": "failed_to_yield",
      "bbox": [
        202,
        133,
        256,
        178
      ]
    },
    {
      "id": 222,
      "type": "car",
      "x_meters": -0.02,
      "y_meters": 0.28,
      "speed_kmh": 0.019999999552965164,
      "acceleration": 0.006000000052154064,
      "jerk": 0.006000000052154064,
      "heading_angle": 0.0,
      "lane_id": 2,
      "lateral_offset": -0.67,
      "distance_to_ego": 0.28,
      "behaviour": "failed_to_yield",
      "bbox": [
        270,
        139,
        294,
        158
      ]
    },
    {
      "id": 296,
      "type": "truck",
      "x_meters": 1.33,
      "y_meters": 2.62,
      "speed_kmh": 0.0,
      "acceleration": 0.0,
      "jerk": 0.0,
      "heading_angle": 0.0,
      "lane_id": 3,
      "lateral_offset": 0.82,
      "distance_to_ego": 2.94,
      "behaviour": "failed_to_yield",
      "bbox": [
        544,
        33,
        617,
        231
      ]
    },
    {
      "id": 299,
      "type": "car",
      "x_meters": -0.01,
      "y_meters": 0.15,
      "speed_kmh": 0.0,
      "acceleration": 0.0,
      "jerk": 0.0,
      "heading_angle": 0.0,
      "lane_id": 2,
      "lateral_offset": -0.46,
      "distance_to_ego": 0.15,
      "behaviour": "failed_to_yield",
      "bbox": [
        289,
        140,
        299,
        152
      ]
    },
    {
      "id": 131,
      "type": "truck",
      "x_meters": 0.01,
      "y_meters": 0.24,
      "speed_kmh": 0.029999999329447746,
      "acceleration": 0.00800000037997961,
      "jerk": 0.010999999940395355,
      "heading_angle": 0.0,
      "lane_id": 2,
      "lateral_offset": 0.32,
      "distance_to_ego": 0.24,
      "behaviour": "failed_to_yield",
      "bbox": [
        321,
        121,
        356,
        156
      ]
    },
    {
      "id": 14,
      "type": "truck",
      "x_meters": 0.35,
      "y_meters": 0.86,
      "speed_kmh": 0.029999999329447746,
      "acceleration": -0.02500000037252903,
      "jerk": -0.04699999839067459,
      "heading_angle": 0.0,
      "lane_id": 3,
      "lateral_offset": -0.08,
      "distance_to_ego": 0.93,
      "behaviour": "yielded",
      "bbox": [
        428,
        0,
        630,
        173
      ]
    },
    {
      "id": 147,
      "type": "car",
      "x_meters": 0.03,
      "y_meters": 0.41,
      "speed_kmh": 0.029999999329447746,
      "acceleration": 0.006000000052154064,
      "jerk": 0.014000000432133675,
      "heading_angle": 0.0,
      "lane_id": 2,
      "lateral_offset": 0.74,
      "distance_to_ego": 0.41,
      "behaviour": "failed_to_yield",
      "bbox": [
        347,
        136,
        378,
        164
      ]
    }
  ]
}