{
  "timestamp": 113,
  "video_source": "20240720_\ud83d\udea8\ud83d\ude91Einsatzfahrt durch ",
  "emergency_active": true,
  "scenario_type": "highway",
  "vehicles": [
    {
      "id": 247,
      "type": "car",
      "x_meters": -2.59,
      "y_meters": 18.66,
      "position_reliable": true,
      "speed_kmh": 2.09,
      "forward_speed_ms": 0.58,
      "lateral_speed_ms": 0.01,
      "acceleration": 0.03,
      "jerk": -0.29,
      "lane_id": 2,
      "lateral_offset": -1.23,
      "distance_to_ego": 18.84,
      "lanes_total": 3,
      "road_type": "highway",
      "lane_source": "config",
      "preceding_id": 316,
      "following_id": 381,
      "left_preceding_id": null,
      "left_following_id": null,
      "right_preceding_id": 355,
      "right_following_id": 14,
      "behaviour": "failed_to_yield",
      "bbox": [
        233,
        136,
        268,
        166
      ]
    },
    {
      "id": 14,
      "type": "car",
      "x_meters": 6.36,
      "y_meters": 13.54,
      "position_reliable": true,
      "speed_kmh": 2.82,
      "forward_speed_ms": 0.7,
      "lateral_speed_ms": 0.35,
      "acceleration": 0.16,
      "jerk": -0.27,
      "lane_id": 3,
      "lateral_offset": 0.47,
      "distance_to_ego": 14.96,
      "lanes_total": 3,
      "road_type": "highway",
      "lane_source": "config",
      "preceding_id": null,
      "following_id": null,
      "left_preceding_id": 247,
      "left_following_id": 315,
      "right_preceding_id": null,
      "right_following_id": null,
      "behaviour": "yielded",
      "bbox": [
        521,
        110,
        600,
        181
      ]
    },
    {
      "id": 315,
      "type": "car",
      "x_meters": 2.21,
      "y_meters": 10.36,
      "position_reliable": true,
      "speed_kmh": 1.1,
      "forward_speed_ms": -0.3,
      "lateral_speed_ms": 0.06,
      "acceleration": -0.09,
      "jerk": -0.04,
      "lane_id": 3,
      "lateral_offset": -1.82,
      "distance_to_ego": 10.59,
      "lanes_total": 3,
      "road_type": "highway",
      "lane_source": "config",
      "preceding_id": 355,
      "following_id": null,
      "left_preceding_id": 247,
      "left_following_id": 381,
      "right_preceding_id": 14,
      "right_following_id": null,
      "behaviour": "yielded",
      "bbox": [
        383,
        131,
        478,
        197
      ]
    },
    {
      "id": 381,
      "type": "car",
      "x_meters": -2.81,
      "y_meters": 9.24,
      "position_reliable": true,
      "speed_kmh": 0.0,
      "forward_speed_ms": 0.0,
      "lateral_speed_ms": 0.0,
      "acceleration": 0.0,
      "jerk": 0.0,
      "lane_id": 1,
      "lateral_offset": 1.03,
      "distance_to_ego": 9.66,
      "lanes_total": 3,
      "road_type": "highway",
      "lane_source": "config",
      "preceding_id": 247,
      "following_id": null,
      "left_preceding_id": null,
      "left_following_id": null,
      "right_preceding_id": 315,
      "right_following_id": null,
      "behaviour": "normal",
      "bbox": [
        121,
        111,
        210,
        206
      ]
    },
    {
      "id": 382,
      "type": "truck",
      "x_meters": 0.69,
      "y_meters": 29.47,
      "position_reliable": true,
      "speed_kmh": 0.0,
      "forward_speed_ms": 0.0,
      "lateral_speed_ms": 0.0,
      "acceleration": 0.0,
      "jerk": 0.0,
      "lane_id": 2,
      "lateral_offset": 0.21,
      "distance_to_ego": 29.48,
      "lanes_total": 3,
      "road_type": "highway",
      "lane_source": "config",
      "preceding_id": null,
      "following_id": 355,
      "left_preceding_id": null,
      "left_following_id": 316,
      "right_preceding_id": 208,
      "right_following_id": 14,
      "behaviour": "normal",
      "bbox": [
        319,
        115,
        345,
        153
      ]
    },
    {
      "id": 316,
      "type": "car",
      "x_meters": -1.91,
      "y_meters": 28.27,
      "position_reliable": true,
      "speed_kmh": 1.75,
      "forward_speed_ms": 0.48,
      "lateral_speed_ms": -0.07,
      "acceleration": -0.28,
      "jerk": -0.93,
      "lane_id": 2,
      "lateral_offset": -0.6,
      "distance_to_ego": 28.33,
      "lanes_total": 3,
      "road_type": "highway",
      "lane_source": "config",
      "preceding_id": null,
      "following_id": 247,
      "left_preceding_id": null,
      "left_following_id": null,
      "right_preceding_id": 382,
      "right_following_id": 355,
      "behaviour": "normal",
      "bbox": [
        279,
        141,
        294,
        153
      ]
    },
    {
      "id": 208,
      "type": "truck",
      "x_meters": 2.65,
      "y_meters": 32.23,
      "position_reliable": true,
      "speed_kmh": 0.59,
      "forward_speed_ms": -0.15,
      "lateral_speed_ms": 0.07,
      "acceleration": -0.128,
      "jerk": -0.038,
      "lane_id": 2,
      "lateral_offset": 0.74,
      "distance_to_ego": 32.34,
      "lanes_total": 3,
      "road_type": "highway",
      "lane_source": "config",
      "preceding_id": null,
      "following_id": 355,
      "left_preceding_id": null,
      "left_following_id": 382,
      "right_preceding_id": null,
      "right_following_id": 14,
      "behaviour": "yielded",
      "bbox": [
        349,
        115,
        375,
        151
      ]
    },
    {
      "id": 355,
      "type": "car",
      "x_meters": 1.14,
      "y_meters": 22.85,
      "position_reliable": true,
      "speed_kmh": 0.98,
      "forward_speed_ms": -0.27,
      "lateral_speed_ms": 0.03,
      "acceleration": -0.09,
      "jerk": -0.03,
      "lane_id": 2,
      "lateral_offset": 0.46,
      "distance_to_ego": 22.88,
      "lanes_total": 3,
      "road_type": "highway",
      "lane_source": "config",
      "preceding_id": 382,
      "following_id": 315,
      "left_preceding_id": 316,
      "left_following_id": 247,
      "right_preceding_id": null,
      "right_following_id": 14,
      "behaviour": "yielded",
      "bbox": [
        336,
        138,
        356,
        160
      ]
    }
  ]
}