{
  "timestamp": 202,
  "video_source": "20240720_\ud83d\udea8\ud83d\ude91Einsatzfahrt durch ",
  "emergency_active": true,
  "emergency_triggered_by": [
    "siren"
  ],
  "scenario_type": "highway",
  "vehicles": [
    {
      "id": 606,
      "type": "car",
      "x_meters": -0.03,
      "y_meters": 0.28,
      "speed_kmh": 0.03999999910593033,
      "acceleration": 0.010999999940395355,
      "jerk": 0.02500000037252903,
      "heading_angle": 0.0,
      "lane_id": 2,
      "lateral_offset": -0.93,
      "distance_to_ego": 0.28,
      "behaviour": "failed_to_yield",
      "bbox": [
        251,
        138,
        283,
        162
      ]
    },
    {
      "id": 198,
      "type": "car",
      "x_meters": -0.19,
      "y_meters": 0.76,
      "speed_kmh": 0.12999999523162842,
      "acceleration": 0.02500000037252903,
      "jerk": 0.04399999976158142,
      "heading_angle": 0.0,
      "lane_id": 1,
      "lateral_offset": 1.5,
      "distance_to_ego": 0.79,
      "behaviour": "failed_to_yield",
      "bbox": [
        150,
        131,
        234,
        195
      ]
    },
    {
      "id": 510,
      "type": "truck",
      "x_meters": 0.32,
      "y_meters": 0.85,
      "speed_kmh": 0.46000000834465027,
      "acceleration": 0.10300000011920929,
      "jerk": 0.210999995470047,
      "heading_angle": 0.0,
      "lane_id": 3,
      "lateral_offset": -0.41,
      "distance_to_ego": 0.91,
      "behaviour": "failed_to_yield",
      "bbox": [
        388,
        0,
        632,
        204
      ]
    },
    {
      "id": 596,
      "type": "car",
      "x_meters": -1.2,
      "y_meters": 20.48,
      "speed_kmh": 0.3499999940395355,
      "acceleration": 0.09700000286102295,
      "jerk": 0.09700000286102295,
      "heading_angle": 0.0,
      "lane_id": 2,
      "lateral_offset": -0.53,
      "distance_to_ego": 1.65,
      "behaviour": "failed_to_yield",
      "bbox": [
        281,
        138,
        299,
        152
      ]
    },
    {
      "id": 343,
      "type": "car",
      "x_meters": -1.01,
      "y_meters": 2.3,
      "speed_kmh": 0.9599999785423279,
      "acceleration": 0.14399999380111694,
      "jerk": 0.3050000071525574,
      "heading_angle": 0.0,
      "lane_id": 1,
      "lateral_offset": -0.22,
      "distance_to_ego": 2.51,
      "behaviour": "failed_to_yield",
      "bbox": [
        0,
        70,
        188,
        230
      ]
    },
    {
      "id": 147,
      "type": "truck",
      "x_meters": 0.07,
      "y_meters": 0.62,
      "speed_kmh": 0.47999998927116394,
      "acceleration": 0.00800000037997961,
      "jerk": -0.10599999874830246,
      "heading_angle": 0.0,
      "lane_id": 2,
      "lateral_offset": 1.04,
      "distance_to_ego": 0.62,
      "behaviour": "yielded",
      "bbox": [
        313,
        46,
        446,
        187
      ]
    }
  ]
}