{
  "timestamp": 485,
  "video_source": "20240720_\ud83d\udea8\ud83d\ude91Einsatzfahrt durch ",
  "emergency_active": true,
  "scenario_type": "highway",
  "vehicles": [
    {
      "id": 1069,
      "type": "truck",
      "x_meters": 2.62,
      "y_meters": 7.05,
      "position_reliable": false,
      "speed_kmh": 0.33,
      "forward_speed_ms": 0.01,
      "lateral_speed_ms": 0.09,
      "acceleration": 0.0,
      "jerk": -0.02,
      "lane_id": 3,
      "lateral_offset": -0.45,
      "distance_to_ego": 7.52,
      "lanes_total": 3,
      "road_type": "highway",
      "lane_source": "config",
      "preceding_id": 1241,
      "following_id": null,
      "left_preceding_id": 1236,
      "left_following_id": null,
      "right_preceding_id": null,
      "right_following_id": null,
      "behaviour": "failed_to_yield",
      "bbox": [
        376,
        0,
        640,
        230
      ]
    },
    {
      "id": 1236,
      "type": "truck",
      "x_meters": -2.33,
      "y_meters": 7.43,
      "position_reliable": true,
      "speed_kmh": 0.97,
      "forward_speed_ms": 0.25,
      "lateral_speed_ms": 0.1,
      "acceleration": 0.14,
      "jerk": 0.05,
      "lane_id": 1,
      "lateral_offset": 0.62,
      "distance_to_ego": 7.79,
      "lanes_total": 3,
      "road_type": "highway",
      "lane_source": "config",
      "preceding_id": null,
      "following_id": null,
      "left_preceding_id": null,
      "left_following_id": null,
      "right_preceding_id": 1241,
      "right_following_id": 1069,
      "behaviour": "yielded",
      "bbox": [
        8,
        0,
        276,
        230
      ]
    },
    {
      "id": 1237,
      "type": "truck",
      "x_meters": 1.03,
      "y_meters": 29.27,
      "position_reliable": true,
      "speed_kmh": 0.48,
      "forward_speed_ms": 0.13,
      "lateral_speed_ms": 0.03,
      "acceleration": -0.57,
      "jerk": 0.42,
      "lane_id": 2,
      "lateral_offset": 0.35,
      "distance_to_ego": 29.29,
      "lanes_total": 3,
      "road_type": "highway",
      "lane_source": "config",
      "preceding_id": null,
      "following_id": 1241,
      "left_preceding_id": null,
      "left_following_id": 1236,
      "right_preceding_id": null,
      "right_following_id": null,
      "behaviour": "normal",
      "bbox": [
        330,
        113,
        350,
        153
      ]
    },
    {
      "id": 1241,
      "type": "truck",
      "x_meters": 1.73,
      "y_meters": 16.53,
      "position_reliable": true,
      "speed_kmh": 1.69,
      "forward_speed_ms": -0.43,
      "lateral_speed_ms": 0.19,
      "acceleration": -0.01,
      "jerk": 0.01,
      "lane_id": 2,
      "lateral_offset": 0.98,
      "distance_to_ego": 16.62,
      "lanes_total": 3,
      "road_type": "highway",
      "lane_source": "config",
      "preceding_id": 1237,
      "following_id": 1069,
      "left_preceding_id": null,
      "left_following_id": 1236,
      "right_preceding_id": null,
      "right_following_id": null,
      "behaviour": "yielded",
      "bbox": [
        357,
        114,
        396,
        172
      ]
    }
  ]
}