{
  "timestamp": 683,
  "video_source": "20240720_\ud83d\udea8\ud83d\ude91Einsatzfahrt durch ",
  "emergency_active": true,
  "scenario_type": "highway",
  "vehicles": [
    {
      "id": 1722,
      "type": "car",
      "x_meters": -2.18,
      "y_meters": 19.01,
      "position_reliable": true,
      "speed_kmh": 1.81,
      "forward_speed_ms": 0.5,
      "lateral_speed_ms": -0.06,
      "acceleration": 0.12,
      "jerk": -0.38,
      "lane_id": 2,
      "lateral_offset": -0.98,
      "distance_to_ego": 19.13,
      "lanes_total": 3,
      "road_type": "highway",
      "lane_source": "config",
      "preceding_id": 1641,
      "following_id": 1672,
      "left_preceding_id": null,
      "left_following_id": null,
      "right_preceding_id": null,
      "right_following_id": 1678,
      "behaviour": "failed_to_yield",
      "bbox": [
        249,
        140,
        279,
        164
      ]
    },
    {
      "id": 1641,
      "type": "car",
      "x_meters": -2.13,
      "y_meters": 22.64,
      "position_reliable": true,
      "speed_kmh": 0.7,
      "forward_speed_ms": -0.18,
      "lateral_speed_ms": -0.07,
      "acceleration": -0.07,
      "jerk": -0.15,
      "lane_id": 2,
      "lateral_offset": -0.9,
      "distance_to_ego": 22.74,
      "lanes_total": 3,
      "road_type": "highway",
      "lane_source": "config",
      "preceding_id": null,
      "following_id": 1722,
      "left_preceding_id": null,
      "left_following_id": null,
      "right_preceding_id": null,
      "right_following_id": 1678,
      "behaviour": "yielded",
      "bbox": [
        261,
        146,
        277,
        161
      ]
    },
    {
      "id": 1672,
      "type": "car",
      "x_meters": -2.26,
      "y_meters": 13.17,
      "position_reliable": true,
      "speed_kmh": 2.16,
      "forward_speed_ms": 0.6,
      "lateral_speed_ms": -0.01,
      "acceleration": 0.17,
      "jerk": -0.47,
      "lane_id": 2,
      "lateral_offset": -1.51,
      "distance_to_ego": 13.36,
      "lanes_total": 3,
      "road_type": "highway",
      "lane_source": "config",
      "preceding_id": 1722,
      "following_id": 1069,
      "left_preceding_id": null,
      "left_following_id": null,
      "right_preceding_id": null,
      "right_following_id": 1678,
      "behaviour": "failed_to_yield",
      "bbox": [
        206,
        135,
        263,
        181
      ]
    },
    {
      "id": 1069,
      "type": "car",
      "x_meters": -2.35,
      "y_meters": 7.38,
      "position_reliable": true,
      "speed_kmh": 1.15,
      "forward_speed_ms": 0.32,
      "lateral_speed_ms": 0.01,
      "acceleration": 0.51,
      "jerk": 0.466,
      "lane_id": 1,
      "lateral_offset": 0.83,
      "distance_to_ego": 7.75,
      "lanes_total": 3,
      "road_type": "highway",
      "lane_source": "config",
      "preceding_id": 1672,
      "following_id": 1426,
      "left_preceding_id": null,
      "left_following_id": null,
      "right_preceding_id": 1237,
      "right_following_id": null,
      "behaviour": "yielded",
      "bbox": [
        89,
        127,
        219,
        227
      ]
    },
    {
      "id": 1426,
      "type": "car",
      "x_meters": -3.69,
      "y_meters": 7.09,
      "position_reliable": false,
      "speed_kmh": 0.27,
      "forward_speed_ms": 0.01,
      "lateral_speed_ms": -0.07,
      "acceleration": 0.0,
      "jerk": 0.005,
      "lane_id": 1,
      "lateral_offset": -1.19,
      "distance_to_ego": 7.99,
      "lanes_total": 3,
      "road_type": "highway",
      "lane_source": "config",
      "preceding_id": 1069,
      "following_id": null,
      "left_preceding_id": null,
      "left_following_id": null,
      "right_preceding_id": 1237,
      "right_following_id": null,
      "behaviour": "yielded",
      "bbox": [
        0,
        162,
        79,
        230
      ]
    },
    {
      "id": 1237,
      "type": "truck",
      "x_meters": 3.93,
      "y_meters": 8.37,
      "position_reliable": false,
      "speed_kmh": 0.13,
      "forward_speed_ms": 0.04,
      "lateral_speed_ms": -0.0,
      "acceleration": 0.01,
      "jerk": 0.018,
      "lane_id": 3,
      "lateral_offset": 0.4,
      "distance_to_ego": 9.25,
      "lanes_total": 3,
      "road_type": "highway",
      "lane_source": "config",
      "preceding_id": null,
      "following_id": null,
      "left_preceding_id": 1678,
      "left_following_id": 1069,
      "right_preceding_id": null,
      "right_following_id": null,
      "behaviour": "failed_to_yield",
      "bbox": [
        473,
        0,
        640,
        230
      ]
    },
    {
      "id": 1678,
      "type": "truck",
      "x_meters": 1.97,
      "y_meters": 12.51,
      "position_reliable": true,
      "speed_kmh": 1.89,
      "forward_speed_ms": 0.52,
      "lateral_speed_ms": -0.1,
      "acceleration": 0.02,
      "jerk": -0.069,
      "lane_id": 2,
      "lateral_offset": 1.35,
      "distance_to_ego": 12.66,
      "lanes_total": 3,
      "road_type": "highway",
      "lane_source": "config",
      "preceding_id": null,
      "following_id": null,
      "left_preceding_id": 1672,
      "left_following_id": 1069,
      "right_preceding_id": null,
      "right_following_id": 1237,
      "behaviour": "failed_to_yield",
      "bbox": [
        317,
        7,
        477,
        185
      ]
    }
  ]
}