{
  "timestamp": 821,
  "video_source": "20240720_\ud83d\udea8\ud83d\ude91Einsatzfahrt durch ",
  "emergency_active": true,
  "emergency_triggered_by": [
    "siren"
  ],
  "scenario_type": "highway",
  "vehicles": [
    {
      "id": 1678,
      "type": "truck",
      "x_meters": 2.42,
      "y_meters": 7.22,
      "speed_kmh": 0.57,
      "forward_speed_ms": -0.15,
      "lateral_speed_ms": 0.05,
      "acceleration": -0.783,
      "jerk": -0.633,
      "heading_angle": 8.13,
      "lane_id": 3,
      "lateral_offset": -0.73,
      "distance_to_ego": 7.61,
      "lanes_total": 3,
      "road_type": "highway",
      "lane_source": "config",
      "preceding_id": 2050,
      "following_id": null,
      "left_preceding_id": 1840,
      "left_following_id": null,
      "right_preceding_id": null,
      "right_following_id": null,
      "behaviour": "failed_to_yield",
      "bbox": [
        362,
        0,
        622,
        228
      ]
    },
    {
      "id": 2050,
      "type": "truck",
      "x_meters": 0.73,
      "y_meters": 19.75,
      "speed_kmh": 0.0,
      "forward_speed_ms": 0.0,
      "lateral_speed_ms": 0.0,
      "acceleration": 0.0,
      "jerk": 0.0,
      "heading_angle": 0.0,
      "lane_id": 2,
      "lateral_offset": 0.33,
      "distance_to_ego": 19.76,
      "lanes_total": 3,
      "road_type": "highway",
      "lane_source": "config",
      "preceding_id": null,
      "following_id": 1678,
      "left_preceding_id": null,
      "left_following_id": 1840,
      "right_preceding_id": null,
      "right_following_id": null,
      "behaviour": "failed_to_yield",
      "bbox": [
        325,
        101,
        353,
        165
      ]
    },
    {
      "id": 1840,
      "type": "truck",
      "x_meters": -2.57,
      "y_meters": 10.34,
      "speed_kmh": 3.6,
      "forward_speed_ms": 0.95,
      "lateral_speed_ms": -0.31,
      "acceleration": 0.608,
      "jerk": 2.577,
      "heading_angle": -103.24,
      "lane_id": 1,
      "lateral_offset": 1.52,
      "distance_to_ego": 10.65,
      "lanes_total": 3,
      "road_type": "highway",
      "lane_source": "config",
      "preceding_id": null,
      "following_id": 2031,
      "left_preceding_id": null,
      "left_following_id": null,
      "right_preceding_id": 2050,
      "right_following_id": 1678,
      "behaviour": "yielded",
      "bbox": [
        139,
        96,
        247,
        198
      ]
    },
    {
      "id": 2031,
      "type": "car",
      "x_meters": -3.03,
      "y_meters": 7.22,
      "speed_kmh": 1.32,
      "forward_speed_ms": 0.14,
      "lateral_speed_ms": -0.34,
      "acceleration": -0.147,
      "jerk": -0.494,
      "heading_angle": 143.13,
      "lane_id": 1,
      "lateral_offset": -0.03,
      "distance_to_ego": 7.83,
      "lanes_total": 3,
      "road_type": "highway",
      "lane_source": "config",
      "preceding_id": 1840,
      "following_id": null,
      "left_preceding_id": null,
      "left_following_id": null,
      "right_preceding_id": 2050,
      "right_following_id": null,
      "behaviour": "yielded",
      "bbox": [
        0,
        64,
        211,
        228
      ]
    }
  ]
}